awsprocesscreds/__init__.py
awsprocesscreds/cache.py
awsprocesscreds/cli.py
awsprocesscreds/compat.py
awsprocesscreds/saml.py
tests/functional/__init__.py
tests/functional/conftest.py
tests/functional/test_saml.py
tests/unit/__init__.py
tests/unit/test_cache.py
tests/unit/test_saml.py
awsprocesscreds-0.0.2.dist-info/LICENSE
awsprocesscreds-0.0.2.dist-info/METADATA
awsprocesscreds-0.0.2.dist-info/NOTICE
awsprocesscreds-0.0.2.dist-info/WHEEL
awsprocesscreds-0.0.2.dist-info/entry_points.txt
awsprocesscreds-0.0.2.dist-info/top_level.txt
awsprocesscreds-0.0.2.dist-info/RECORD
