Metadata-Version: 2.1
Name: awsprocesscreds
Version: 0.0.2
Summary: AWS Process Credential Providers.
Home-page: https://github.com/awslabs/awsprocesscreds
Author: Amazon Web Services
Author-email: UNKNOWN
License: Apache License 2.0
Keywords: aws credentials
Platform: UNKNOWN
Classifier: Development Status :: 2 - Pre-Alpha
Classifier: Intended Audience :: Developers
Classifier: Intended Audience :: System Administrators
Classifier: Natural Language :: English
Classifier: License :: OSI Approved :: Apache Software License
Classifier: Programming Language :: Python
Classifier: Programming Language :: Python :: 2.7
Classifier: Programming Language :: Python :: 3
Classifier: Programming Language :: Python :: 3.3
Classifier: Programming Language :: Python :: 3.4
Classifier: Programming Language :: Python :: 3.5
Classifier: Programming Language :: Python :: 3.6
Requires-Dist: botocore (<2.0.0,>=1.8.1)
Requires-Dist: six (<2.0.0,>=1.8.0)
Requires-Dist: requests (<3.0.0,>=2.7.0)
